digitalwallet/main.py
digitalwallet/models/__init__.py
digitalwallet/models/models.py
digitalwallet/models/wallet.py
digitalwallet/models/wallet_interface.py
digitalwallet/service/__init__.py
digitalwallet/service/api.py
digitalwallet/service/fetcher.py
digitalwallet/utils/__init__.py
digitalwallet/utils/cli.py
digitalwallet/utils/logger.py
digitalwallet-0.0.3.dist-info/METADATA
digitalwallet-0.0.3.dist-info/WHEEL
digitalwallet-0.0.3.dist-info/RECORD
