Metadata-Version: 2.1
Name: DigitalWallet
Version: 0.0.3
Summary: DigitalWallet is an async service that counts your currencies.
Author: heliosgrounder
Requires-Python: >=3.8,<3.12
Classifier: Programming Language :: Python :: 3
Classifier: Programming Language :: Python :: 3.8
Classifier: Programming Language :: Python :: 3.9
Classifier: Programming Language :: Python :: 3.10
Classifier: Programming Language :: Python :: 3.11
Requires-Dist: fastapi (==0.111.1)
Requires-Dist: httpx (==0.27.0)
Requires-Dist: pydantic (==2.8.2)
